{
  "_fv": 66,
  "_type": "musicdisc",
  "definition": {
    "name": "In a Rush (2023)",
    "rarity": "RARE",
    "texture": "singles1",
    "description": "Vylet Pony - In a Rush (2023)",
    "creativeTabs": [
      {
        "value": "CUSTOM:MagitechEraCreativeTab"
      }
    ],
    "specialInformation": {
      "fixedValue": [
        "Remaster of 11-24-17 release",
        "06-07-23"
      ]
    },
    "glowCondition": {
      "fixedValue": false
    },
    "music": {
      "value": "CUSTOM:vyletpony_single_inarush2023"
    },
    "lengthInTicks": 4865,
    "analogOutput": 6
  }
}